unihttp/__init__.py
unihttp/bind_method.py
unihttp/exceptions.py
unihttp/markers.py
unihttp/method.py
unihttp/py.typed
unihttp/serialize.py
unihttp/clients/__init__.py
unihttp/clients/aiohttp.py
unihttp/clients/base.py
unihttp/clients/httpx.py
unihttp/clients/niquests.py
unihttp/clients/requests.py
unihttp/http/__init__.py
unihttp/http/files.py
unihttp/http/request.py
unihttp/http/response.py
unihttp/middlewares/__init__.py
unihttp/middlewares/base.py
unihttp/middlewares/error_mapper.py
unihttp/middlewares/logging.py
unihttp/middlewares/retry.py
unihttp/serializers/adaptix/__init__.py
unihttp/serializers/adaptix/fixed_tp_tags_unwrapping.py
unihttp/serializers/adaptix/marker_tools.py
unihttp/serializers/adaptix/omitted.py
unihttp/serializers/adaptix/provider.py
unihttp/serializers/adaptix/serialize.py
unihttp-0.2.1.dist-info/METADATA
unihttp-0.2.1.dist-info/WHEEL
unihttp-0.2.1.dist-info/licenses/LICENSE
unihttp-0.2.1.dist-info/RECORD
