Metadata-Version: 2.4
Name: unihttp
Version: 0.2.1
Summary: A modern and fast library for developing API clients.
Project-URL: Homepage, https://github.com/goduni/unihttp
Project-URL: Repository, https://github.com/goduni/unihttp
Project-URL: Issues, https://github.com/goduni/unihttp/issues
Author-email: Universe Interface <uni@goduni.me>
License: MIT
License-File: LICENSE
Keywords: adaptix,api,async,client,declarative,decorator,http,rest,sdk
Classifier: Development Status :: 3 - Alpha
Classifier: Framework :: AsyncIO
Classifier: Intended Audience :: Developers
Classifier: License :: OSI Approved :: MIT License
Classifier: Operating System :: OS Independent
Classifier: Programming Language :: Python :: 3.12
Classifier: Programming Language :: Python :: 3.13
Classifier: Programming Language :: Python :: 3.14
Classifier: Topic :: Internet :: WWW/HTTP
Classifier: Topic :: Software Development :: Libraries :: Python Modules
Classifier: Typing :: Typed
Requires-Python: <3.15,>=3.12
Requires-Dist: adaptix>=3.0.0b11
Provides-Extra: aiohttp
Requires-Dist: aiohttp>=3.10.0; extra == 'aiohttp'
Provides-Extra: httpx
Requires-Dist: httpx>=0.28.1; extra == 'httpx'
Provides-Extra: niquests
Requires-Dist: niquests>=3.17.0; extra == 'niquests'
Provides-Extra: requests
Requires-Dist: requests>=2.32.0; extra == 'requests'
